[
  {
    "batch_id": "alfa-1761133320-66974519",
    "duration_ms": 0,
    "ritual": "forge",
    "schema_version": "1.0",
    "status": "success",
    "units_processed": 1
  },
  {
    "batch_id": "alfa-1761133332-1e8cf793",
    "duration_ms": 0,
    "ritual": "forge",
    "schema_version": "1.0",
    "status": "success",
    "units_processed": 1
  },
  {
    "batch_id": "alfa-1761133344-328549e2",
    "duration_ms": 0,
    "ritual": "forge",
    "schema_version": "1.0",
    "status": "success",
    "units_processed": 1
  }
]
